lanyard/__init__.py
lanyard/client.py
lanyard/config.py
lanyard/constant.py
lanyard/enum.py
lanyard/exception.py
lanyard/model.py
lanyard/decorator/__init__.py
lanyard/decorator/handle_error.py
lanyard/decorator/requires_token.py
lanyard/http/__init__.py
lanyard/http/base.py
lanyard/http/exception.py
lanyard/http/response.py
lanyard/http/decorator/__init__.py
lanyard/http/decorator/handle_error.py
lanyard/http/httpx/__init__.py
lanyard/http/httpx/exception.py
lanyard/http/httpx/httpx.py
lanyard/http/type/__init__.py
lanyard/http/type/data.py
lanyard/http/type/headers.py
lanyard/http/type/params.py
lanyard/service/__init__.py
lanyard/service/base.py
lanyard/service/context.py
lanyard/service/kv.py
lanyard/service/user.py
lanyard/type/__init__.py
lanyard/type/snowflake.py
lanyard_py-1.0.1.dist-info/licenses/LICENSE
lanyard_py-1.0.1.dist-info/METADATA
lanyard_py-1.0.1.dist-info/WHEEL
lanyard_py-1.0.1.dist-info/top_level.txt
lanyard_py-1.0.1.dist-info/RECORD
